GenProcTrees/__init__.py
GenProcTrees/branch.py
GenProcTrees/gen_proc_trees.py
GenProcTrees/geometry_writer.py
GenProcTrees/image_writer.py
GenProcTrees/leaf.py
GenProcTrees/tree.py
GenProcTrees-0.0.1.dev1.dist-info/LICENSE.txt
GenProcTrees-0.0.1.dev1.dist-info/METADATA
GenProcTrees-0.0.1.dev1.dist-info/RECORD
GenProcTrees-0.0.1.dev1.dist-info/WHEEL
GenProcTrees-0.0.1.dev1.dist-info/top_level.txt
