Metadata-Version: 2.1
Name: GenProcTrees
Version: 0.0.1.dev1
Summary: Procedurally generate semi-realistic trees
Home-page: https://github.com/KolijnWolfaardt/GenProcTrees
Author: Kolijn Wolfaardt
License: UNKNOWN
Keywords: procedural generation tree
Platform: UNKNOWN
Classifier: Development Status :: 3 - Alpha
Classifier: Intended Audience :: Developers
Classifier: Topic :: Artistic Software
Classifier: Topic :: Multimedia :: Graphics :: 3D Modeling
Classifier: License :: OSI Approved :: MIT License
Classifier: Programming Language :: Python :: 3.5
Classifier: Programming Language :: Python :: 3.6
Requires-Dist: numpy
Requires-Dist: scipy
Requires-Dist: Pillow
